pyarrow_assert/__init__.py
pyarrow_assert/main.py
pyarrow_assert-0.4.1.dist-info/METADATA
pyarrow_assert-0.4.1.dist-info/WHEEL
pyarrow_assert-0.4.1.dist-info/entry_points.txt
pyarrow_assert-0.4.1.dist-info/top_level.txt
pyarrow_assert-0.4.1.dist-info/RECORD
